pca/packages/errors/__init__.py
pca/packages/errors/boundary.py
pca/packages/errors/builder.py
pca/packages/errors/catalog.py
pca/packages/errors/types.py
pca_errors-0.2.0.dist-info/LICENSE
pca_errors-0.2.0.dist-info/WHEEL
pca_errors-0.2.0.dist-info/METADATA
pca_errors-0.2.0.dist-info/RECORD
